setup.py
commons/__init__.py
python_commons2.egg-info/PKG-INFO
python_commons2.egg-info/SOURCES.txt
python_commons2.egg-info/dependency_links.txt
python_commons2.egg-info/requires.txt
python_commons2.egg-info/top_level.txt