Metadata-Version: 1.0
Name: python-commons2
Version: 0.1
Summary: Some common utility methods I use often
Home-page: http://github.com/Moshe-Immerman/python-commons
Author: Moshe Immerman
Author-email: name.surname@gmail.com
License: BSD
Platform: any
